[
  {
    "image": "Gà rán_1.jpg",
    "huggingface": "fried chicken wings on a wooden cutting board",
    "folder": "Gà rán_20_7_2023_14_7_25"
  },
  {
    "image": "Gà rán_2.jpg",
    "huggingface": "a basket full of fried chicken in a kitchen",
    "folder": "Gà rán_20_7_2023_14_7_25"
  },
  {
    "image": "Gà rán_3.jpg",
    "huggingface": "chicken wings in a pan with sesame and sesame",
    "folder": "Gà rán_20_7_2023_14_7_25"
  },
  {
    "image": "Gà rán_5.jpg",
    "huggingface": "chicken wings with rice and sauce",
    "folder": "Gà rán_20_7_2023_14_7_25"
  }
]